ropper/__init__.py
ropper/__main__.py
ropper/arch.py
ropper/console.py
ropper/gadget.py
ropper/options.py
ropper/rop.py
ropper/search.py
ropper/semantic.py
ropper/service.py
ropper/z3helper.py
ropper-1.13.12.dist-info/AUTHORS
ropper-1.13.12.dist-info/COPYING
ropper-1.13.12.dist-info/METADATA
ropper-1.13.12.dist-info/WHEEL
ropper-1.13.12.dist-info/entry_points.txt
ropper-1.13.12.dist-info/top_level.txt
ropper-1.13.12.dist-info/RECORD
