Metadata-Version: 2.2
Name: ropper
Version: 1.13.12
Summary: Show information about files in different file formats and find gadgets to build rop chains for different architectures.
Author-email: Sascha Schirra <sashs@scoding.de>
Maintainer-email: Sascha Schirra <sashs@scoding.de>
License: BSD
Project-URL: Homepage, http://scoding.de/ropper/
Project-URL: Repository, https://github.com/sashs/Ropper.git
Classifier: Topic :: Security
Classifier: Environment :: Console
Classifier: Operating System :: OS Independent
Classifier: License :: OSI Approved :: BSD License
Classifier: Programming Language :: Python
Classifier: Intended Audience :: Developers
Requires-Python: >=3
License-File: COPYING
License-File: AUTHORS
Requires-Dist: filebytes>=0.10.0
Requires-Dist: capstone>=3
Provides-Extra: ropchain
Requires-Dist: keystone-engine; extra == "ropchain"
